wagtail_colour_picker_enoki/__init__.py
wagtail_colour_picker_enoki/conf.py
wagtail_colour_picker_enoki/forms.py
wagtail_colour_picker_enoki/models.py
wagtail_colour_picker_enoki/urls.py
wagtail_colour_picker_enoki/views.py
wagtail_colour_picker_enoki/wagtail_hooks.py
wagtail_colour_picker_enoki/static/colourpicker/css/colourpicker.css
wagtail_colour_picker_enoki/static/colourpicker/js/chooser.js
wagtail_colour_picker_enoki/static/colourpicker/js/colourpicker.js
wagtail_colour_picker_enoki/templates/colourpicker/chooser/chooser.html
wagtail_colour_picker_enoki/templates/colourpicker/chooser/chosen.js
wagtail_colour_picker_enoki/templates/colourpicker/forms/widgets/colour_option.html
wagtail_colour_picker_enoki/utils/__init__.py
wagtail_colour_picker_enoki/utils/colour.py
wagtail_colour_picker_enoki/utils/version.py
wagtail_colour_picker_enoki-0.3.2.dist-info/LICENSE.txt
wagtail_colour_picker_enoki-0.3.2.dist-info/METADATA
wagtail_colour_picker_enoki-0.3.2.dist-info/WHEEL
wagtail_colour_picker_enoki-0.3.2.dist-info/top_level.txt
wagtail_colour_picker_enoki-0.3.2.dist-info/RECORD
